auruminstaller/__init__.py
auruminstaller/main.py
auruminstaller-0.1.0.dist-info/METADATA
auruminstaller-0.1.0.dist-info/WHEEL
auruminstaller-0.1.0.dist-info/entry_points.txt
auruminstaller-0.1.0.dist-info/RECORD
