Metadata-Version: 2.1
Name: auruminstaller
Version: 0.1.0
Summary: aurumOS Operating System Installer
Author: Andrew Murha
Author-email: theyoungdevel@duck.com
Requires-Python: >=3.11,<4.0
Classifier: Programming Language :: Python :: 3
Classifier: Programming Language :: Python :: 3.11
Classifier: Programming Language :: Python :: 3.12
Requires-Dist: flet (>=0.19.0,<0.20.0)
